aslan/__init__.py
aslan/__main__.py
aslan/aslan_parser.py
aslan/recent_items.py
aslan/utils.py
aslan-0.0.12.dist-info/LICENSE.md
aslan-0.0.12.dist-info/METADATA
aslan-0.0.12.dist-info/WHEEL
aslan-0.0.12.dist-info/RECORD
