Metadata-Version: 2.1
Name: aslan
Version: 0.0.12
Summary: Parser for ASLAN
License: See LICENSE.md
Author: Jerzy Foss
Author-email: 44465055+jayfoss@users.noreply.github.com
Requires-Python: >=3.9,<4.0
Classifier: License :: Other/Proprietary License
Classifier: Programming Language :: Python :: 3
Classifier: Programming Language :: Python :: 3.9
Classifier: Programming Language :: Python :: 3.10
Classifier: Programming Language :: Python :: 3.11
Classifier: Programming Language :: Python :: 3.12
